django_qstash/__init__.py
django_qstash/callbacks.py
django_qstash/client.py
django_qstash/cron.py
django_qstash/exceptions.py
django_qstash/handlers.py
django_qstash/logging.py
django_qstash/py.typed
django_qstash/settings.py
django_qstash/signals.py
django_qstash/urls.py
django_qstash/utils.py
django_qstash/views.py
django_qstash/app/__init__.py
django_qstash/app/base.py
django_qstash/app/decorators.py
django_qstash/db/__init__.py
django_qstash/db/models.py
django_qstash/discovery/__init__.py
django_qstash/discovery/fields.py
django_qstash/discovery/models.py
django_qstash/discovery/utils.py
django_qstash/discovery/validators.py
django_qstash/management/__init__.py
django_qstash/management/commands/__init__.py
django_qstash/management/commands/available_tasks.py
django_qstash/management/commands/clear_stale_results.py
django_qstash/management/commands/task_schedules.py
django_qstash/results/__init__.py
django_qstash/results/admin.py
django_qstash/results/apps.py
django_qstash/results/models.py
django_qstash/results/services.py
django_qstash/results/tasks.py
django_qstash/results/migrations/0001_initial.py
django_qstash/results/migrations/0002_taskresult_function_path_alter_taskresult_status_and_more.py
django_qstash/results/migrations/__init__.py
django_qstash/schedules/__init__.py
django_qstash/schedules/admin.py
django_qstash/schedules/apps.py
django_qstash/schedules/exceptions.py
django_qstash/schedules/formatters.py
django_qstash/schedules/forms.py
django_qstash/schedules/models.py
django_qstash/schedules/services.py
django_qstash/schedules/signals.py
django_qstash/schedules/validators.py
django_qstash/schedules/migrations/0001_initial.py
django_qstash/schedules/migrations/0002_taskschedule_updated_at.py
django_qstash/schedules/migrations/0003_alter_taskschedule_cron.py
django_qstash/schedules/migrations/__init__.py
django_qstash-0.2.4.dist-info/METADATA
django_qstash-0.2.4.dist-info/WHEEL
django_qstash-0.2.4.dist-info/top_level.txt
django_qstash-0.2.4.dist-info/RECORD
