Metadata-Version: 2.4
Name: django-qstash
Version: 0.2.4
Summary: A drop-in replacement for Celery's shared_task with Upstash QStash.
Author-email: Justin Mitchel <justin@codingforentrepreneurs.com>
Project-URL: Changelog, https://github.com/jmitchel3/django-qstash
Project-URL: Documentation, https://github.com/jmitchel3/django-qstash
Project-URL: Funding, https://github.com/jmitchel3/django-qstash
Project-URL: Repository, https://github.com/jmitchel3/django-qstash
Classifier: Development Status :: 5 - Production/Stable
Classifier: Framework :: Django :: 4.2
Classifier: Framework :: Django :: 5.0
Classifier: Framework :: Django :: 5.1
Classifier: Framework :: Django :: 5.2
Classifier: Framework :: Django :: 6.0
Classifier: Intended Audience :: Developers
Classifier: License :: OSI Approved :: MIT License
Classifier: Natural Language :: English
Classifier: Operating System :: OS Independent
Classifier: Programming Language :: Python :: 3 :: Only
Classifier: Programming Language :: Python :: 3.10
Classifier: Programming Language :: Python :: 3.11
Classifier: Programming Language :: Python :: 3.12
Classifier: Programming Language :: Python :: 3.13
Classifier: Programming Language :: Python :: 3.14
Classifier: Programming Language :: Python :: Implementation :: CPython
Requires-Python: >=3.10
Requires-Dist: django>=4.2
Requires-Dist: qstash<3,>=2
Requires-Dist: requests>=2.30
